matchlight/__init__.py
matchlight/alert.py
matchlight/assets.py
matchlight/connection.py
matchlight/error.py
matchlight/matches.py
matchlight/utils.py
pylibfp/__init__.py
pylibfp/checklibfp.py
pylibfp/lib/libfpd64.so
pylibfp/lib/libfpl64.so
pylibfp/lib/libfpw32.dll
pylibfp/lib/libfpw64.dll
matchlightsdk-2021.10.14.2.dist-info/LICENSE
matchlightsdk-2021.10.14.2.dist-info/LICENSES
matchlightsdk-2021.10.14.2.dist-info/METADATA
matchlightsdk-2021.10.14.2.dist-info/WHEEL
matchlightsdk-2021.10.14.2.dist-info/top_level.txt
matchlightsdk-2021.10.14.2.dist-info/RECORD
